LICENSE
MANIFEST.in
README.rst
setup.py
django_phonenumber_filter.egg-info/PKG-INFO
django_phonenumber_filter.egg-info/SOURCES.txt
django_phonenumber_filter.egg-info/dependency_links.txt
django_phonenumber_filter.egg-info/requires.txt
django_phonenumber_filter.egg-info/top_level.txt
phonenumber_filter/__init__.py
phonenumber_filter/tests.py
phonenumber_filter/templatetags/__init__.py
phonenumber_filter/templatetags/phonenumber_filters.py