Metadata-Version: 1.1
Name: django-phonenumber-filter
Version: 1.0.0
Summary: A simple Django filter that will format and print a phone number in a template.
Home-page: http://github.com/foundertherapy/django-phonenumber-filter/
Author: Dana Spiegel
Author-email: dana@foundertherapy.co
License: UNKNOWN
Download-URL: https://github.com/foundertherapy/django-phonenumber-filter/archive/1.0.0.tar.gz
Keywords: phonenumber,django,filter,format
Platform: UNKNOWN
